SendgridNotificationSystem/SendgridNotificationSystem.py
SendgridNotificationSystem/__init__.py
covenirbpo_projects_sendgridnotificationsystem-1.0.0.dist-info/METADATA
covenirbpo_projects_sendgridnotificationsystem-1.0.0.dist-info/WHEEL
covenirbpo_projects_sendgridnotificationsystem-1.0.0.dist-info/licenses/LICENSE
covenirbpo_projects_sendgridnotificationsystem-1.0.0.dist-info/RECORD
