Metadata-Version: 2.1
Name: CovenirBPO.projects.SendgridNotificationSystem
Version: 1.0.0
Summary: A small package that supports sending email notifications via sendgrid
Author-email: "Joshua H. Santiago" <joshua.santiago@covenirbpo.com>
License-File: LICENSE
Classifier: License :: OSI Approved :: MIT License
Classifier: Operating System :: OS Independent
Classifier: Programming Language :: Python :: 3
Requires-Python: >=3.8
